README.md
setup.cfg
setup.py
StringBuilder/__init__.py
StringBuilder/string_builder.py
StringBuilder.egg-info/PKG-INFO
StringBuilder.egg-info/SOURCES.txt
StringBuilder.egg-info/dependency_links.txt
StringBuilder.egg-info/top_level.txt
test/test_string_builder.py