Metadata-Version: 1.0
Name: StringBuilder
Version: 1.0.0a4
Summary: library for efficient string building
Home-page: https://github.com/Tarrasse/string_builder
Author: Mahmoud El-Tarrasse
Author-email: Mahmoudtarrasse@gmail.com
License: MIT
Keywords: python,string,appending,building
Platform: UNKNOWN
